gojan/__init__.py
gojan/utils.py
gojan-0.1.1.dist-info/METADATA
gojan-0.1.1.dist-info/WHEEL
gojan-0.1.1.dist-info/top_level.txt
gojan-0.1.1.dist-info/RECORD
